Metadata-Version: 1.1
Name: simplemysql
Version: 0.4
Summary: An ultra simple wrapper for Python MySQLdb with very basic functionality
Home-page: http://nadh.in/code/simplemysql
Author: Kailash Nadh
Author-email: kailash.nadh@gmail.com
License: GPLv2
Download-URL: http://github.com/knadh/simplemysql
Platform: UNKNOWN
Classifier: Development Status :: 3 - Alpha
Classifier: Intended Audience :: Developers
Classifier: Programming Language :: Python
Classifier: Natural Language :: English
Classifier: License :: OSI Approved :: GNU General Public License v2 (GPLv2)
Classifier: Programming Language :: Python :: 2.6
Classifier: Programming Language :: Python :: 2.7
Classifier: Topic :: Software Development :: Libraries :: Python Modules
Classifier: Topic :: Database
Classifier: Topic :: Software Development :: Libraries
